rackspace_backup_client-0.19.3.dist-info/pydist.json
rackspace_backup_client-0.19.3.dist-info/RECORD
rackspace_backup_client-0.19.3.dist-info/METADATA
rackspace_backup_client-0.19.3.dist-info/top_level.txt
rackspace_backup_client-0.19.3.dist-info/DESCRIPTION.rst
rackspace_backup_client-0.19.3.dist-info/WHEEL
rcbu/__init__.py
rcbu/version.py
rcbu/utils/__init__.py
rcbu/utils/perf.py
rcbu/utils/date.py
rcbu/utils/bytes.py
rcbu/common/activity_mixin.py
rcbu/common/constants.py
rcbu/common/duration.py
rcbu/common/exceptions.py
rcbu/common/http.py
rcbu/common/activity.py
rcbu/common/weekdays.py
rcbu/common/__init__.py
rcbu/common/status.py
rcbu/common/auth.py
rcbu/common/schedule.py
rcbu/common/assertions.py
rcbu/client/restore.py
rcbu/client/agent.py
rcbu/client/command.py
rcbu/client/connection.py
rcbu/client/restore_report.py
rcbu/client/__init__.py
rcbu/client/backup_configuration.py
rcbu/client/report.py
rcbu/client/client.py
rcbu/client/backup.py
rcbu/client/backup_report.py
tests/__init__.py
tests/integration/test_backup_configuration.py
tests/integration/__init__.py
tests/utils/agent.py
tests/utils/__init__.py
tests/utils/credentials.py
tests/mock/restore.py
tests/mock/rsa.py
tests/mock/agent.py
tests/mock/activity.py
tests/mock/__init__.py
tests/mock/configuration.py
tests/mock/report.py
tests/mock/auth.py
tests/mock/schedule.py
tests/unit/__init__.py
tests/unit/utils/__init__.py
tests/unit/utils/test_bytes.py
tests/unit/utils/test_perf.py
tests/unit/common/test_activity_mixin.py
tests/unit/common/test_activity.py
tests/unit/common/test_assertions.py
tests/unit/common/__init__.py
tests/unit/common/test_schedule.py
tests/unit/common/test_duration.py
tests/unit/common/test_auth.py
tests/unit/client/test_restore_report.py
tests/unit/client/test_restore.py
tests/unit/client/test_agent.py
tests/unit/client/test_backup_configuration.py
tests/unit/client/test_backup.py
tests/unit/client/__init__.py
tests/unit/client/test_connection.py
tests/unit/client/test_backup_report.py
tests/unit/client/test_command.py
tests/smoke/__init__.py
tests/smoke/test_connect.py
tests/smoke/test_client.py
rackspace_backup_client-0.19.3.data/data/setup.py
