Metadata-Version: 2.0
Name: rackspace-backup-client
Version: 0.19.3
Summary: A Python client for the Rackspace Cloud Backup API.
Home-page: https://github.com/rackerlabs/python-cloudbackup-sdk
Author: Alejandro Cabrera
Author-email: alejandro.cabrera@rackspace.com
License: Apache License (2.0)
Keywords: rackspace,Cloud Backup,client
Platform: UNKNOWN
Classifier: Development Status :: 4 - Beta
Classifier: License :: OSI Approved :: Apache Software License
Classifier: Environment :: Console
Classifier: Operating System :: OS Independent
Classifier: Intended Audience :: Developers
Classifier: Intended Audience :: System Administrators
Classifier: Programming Language :: Python :: 2.7
Classifier: Programming Language :: Python :: 3.3
Classifier: Programming Language :: Python :: Implementation :: CPython
Requires-Dist: enum34 (>=0.9)
Requires-Dist: pycrypto (>=2.6.1)
Requires-Dist: python-dateutil (>=2.2)
Requires-Dist: requests (>=2.1.0)
